chdv/__init__.py
chdv/clibs/__init__.py
chdv/clibs/condition_codes.clib
chdv/clibs/curry_and_treehash.clib
chdv/clibs/sha256tree.clib
chdv/clibs/singleton_truths.clib
chdv/clibs/utility_macros.clib
chdv/cmds/__init__.py
chdv/cmds/chinilla_inspect.py
chdv/cmds/cli.py
chdv/cmds/clsp.py
chdv/cmds/rpc.py
chdv/cmds/sim.py
chdv/cmds/sim_utils.py
chdv/cmds/util.py
chdv/examples/__init__.py
chdv/examples/clsp/__init__.py
chdv/examples/clsp/piggybank.clsp
chdv/examples/clsp/piggybank.clsp.hex
chdv/examples/clvm/__init__.py
chdv/examples/drivers/__init__.py
chdv/examples/drivers/piggybank_drivers.py
chdv/test/__init__.py
chdv/test/test_skeleton.py
chdv/util/__init__.py
chdv/util/keys.py
chdv/util/load_clvm.py
chinilla_dev_tools-1.3.dist-info/LICENSE
chinilla_dev_tools-1.3.dist-info/METADATA
chinilla_dev_tools-1.3.dist-info/WHEEL
chinilla_dev_tools-1.3.dist-info/entry_points.txt
chinilla_dev_tools-1.3.dist-info/top_level.txt
chinilla_dev_tools-1.3.dist-info/RECORD
