Metadata-Version: 2.1
Name: chinilla-dev-tools
Version: 1.3
Summary: Chinilla development commands
Home-page: https://github.com/Chinilla
Author: Edward Teach
Author-email: edward@chinilla.com
License: https://opensource.org/licenses/Apache-2.0
Project-URL: Bug Reports, https://github.com/Chinilla/chinilla-dev-tools
Project-URL: Source, https://github.com/Chinilla/chinilla-dev-tools
Classifier: Programming Language :: Python :: 3
Classifier: Programming Language :: Python :: 3.8
Classifier: Programming Language :: Python :: 3.9
Classifier: License :: OSI Approved :: Apache Software License
Classifier: Topic :: Security :: Cryptography
License-File: LICENSE
Requires-Dist: chinilla-blockchain (==1.3.0)
Requires-Dist: packaging
Requires-Dist: pytest
Requires-Dist: pytest-asyncio
Requires-Dist: pytimeparse
Provides-Extra: dev
Requires-Dist: flake8 ; extra == 'dev'
Requires-Dist: mypy ; extra == 'dev'
Requires-Dist: types-aiofiles ; extra == 'dev'
Requires-Dist: types-click ; extra == 'dev'
Requires-Dist: types-cryptography ; extra == 'dev'
Requires-Dist: types-pkg-resources ; extra == 'dev'
Requires-Dist: types-pyyaml ; extra == 'dev'
Requires-Dist: types-setuptools ; extra == 'dev'
Requires-Dist: black (==21.12b0) ; extra == 'dev'
Requires-Dist: isort ; extra == 'dev'
Requires-Dist: pre-commit ; extra == 'dev'
Requires-Dist: pylint ; extra == 'dev'
